simplegoogleapi/__init__.py
simplegoogleapi/client.py
simple_googleapi_client-1.0.dist-info/METADATA
simple_googleapi_client-1.0.dist-info/WHEEL
simple_googleapi_client-1.0.dist-info/top_level.txt
simple_googleapi_client-1.0.dist-info/RECORD
